ecmhongz/__init__.py
ecmhongz/monitor.py
ecmhongz-0.2.1.dist-info/METADATA
ecmhongz-0.2.1.dist-info/WHEEL
ecmhongz-0.2.1.dist-info/top_level.txt
ecmhongz-0.2.1.dist-info/RECORD
