Metadata-Version: 2.1
Name: ecmhongz
Version: 0.2.1
Summary: ecmhongz is a Python package for Energy Consumption Monitoring created by HongzhenHuang.
Home-page: https://github.com/SusCom-Lab/ECM-Tool
Author: HongzhenHuang
Author-email: 202130500072@mail.scut.edn.cn
Classifier: Programming Language :: Python :: 3
Classifier: License :: OSI Approved :: MIT License
Classifier: Operating System :: OS Independent
Requires-Python: >=3.7
Requires-Dist: psutil
Requires-Dist: mysql-connector-python
Requires-Dist: pandas
Requires-Dist: plotly
Requires-Dist: deprecated
Requires-Dist: numpy
